earthshot/__init__.py
earthshot/core/__init__.py
earthshot/core/mon_stats.py
earthshot/core/normalize.py
earthshot/tests/__init__.py
earthshot/tests/test_basic_functionality.py
earthshot/tests/test_ee_api.py
earthshot/water/__init__.py
earthshot/water/water_common.py
earthshot/water/water_viz.py
earthshot-0.0.4.dist-info/METADATA
earthshot-0.0.4.dist-info/WHEEL
earthshot-0.0.4.dist-info/top_level.txt
earthshot-0.0.4.dist-info/RECORD
